{
  "case_id": "Case_4",
  "model_id": "mistralai/mistral-large-2411",
  "content": "```json\n{\n    \"primary_diagnosis\": {\n        \"name\": \"McArdle Disease (Glycogen Storage Disease Type V)\",\n        \"confidence\": 0.8,\n        \"icd_code\": \"E74.01\",\n        \"reasoning\": \"Exercise intolerance, intermittent muscle weakness, dark urine post-exercise, elevated CK levels during episodes, and consanguineous parents suggest a genetic metabolic disorder.\"\n    },\n    \"differential_diagnoses\": [\n        {\n            \"name\": \"Carnitine Palmitoyltransferase II Deficiency (CPT II)\",\n            \"confidence\": 0.6,\n            \"icd_code\": \"E71.311\",\n            \"reasoning\": \"Similar symptoms of exercise-induced muscle weakness and dark urine, but less likely due to the prolonged duration of symptoms.\"\n        },\n        {\n            \"name\": \"Myoadenylate Deaminase Deficiency\",\n            \"confidence\": 0.4,\n            \"icd_code\": \"E74.8\",\n            \"reasoning\": \"Can cause exercise intolerance and muscle weakness, but typically does not cause dark urine.\"\n        },\n        {\n            \"name\": \"Tarui Disease (Glycogen Storage Disease Type VII)\",\n            \"confidence\": 0.3,\n            \"icd_code\": \"E74.02\",\n            \"reasoning\": \"Similar symptoms but less common and usually presents with hemolytic anemia.\"\n        }\n    ],\n    \"key_findings\": [\n        \"Exercise intolerance\",\n        \"Intermittent muscle weakness\",\n        \"Dark urine after intense training\",\n        \"Elevated CK levels during episodes\",\n        \"Consanguineous parents\"\n    ],\n    \"diagnostic_tests\": [\n        {\n            \"test\": \"Genetic Testing for GSD Type V\",\n            \"purpose\": \"Confirm McArdle Disease\",\n            \"priority\": \"urgent\"\n        },\n        {\n            \"test\": \"Muscle Biopsy\",\n            \"purpose\": \"Evaluate for glycogen storage abnormalities\",\n            \"priority\": \"urgent\"\n        },\n        {\n            \"test\": \"Urine Myoglobin Test\",\n            \"purpose\": \"Confirm myoglobinuria\",\n            \"priority\": \"immediate\"\n        }\n    ],\n    \"management_plan\": {\n        \"immediate_actions\": [\n            \"Rest and avoid intense physical activity\",\n            \"Hydration and dietary modifications\"\n        ],\n        \"medications\": [\n            {\n                \"drug\": \"N/A\",\n                \"dose\": \"N/A\",\n                \"route\": \"N/A\",\n                \"duration\": \"N/A\",\n                \"rationale\": \"No specific medications for McArdle Disease; management is primarily through lifestyle modifications\"\n            }\n        ],\n        \"monitoring\": [\n            \"CK levels during and between episodes\",\n            \"Frequency: During episodes and routinely thereafter\"\n        ],\n        \"consultations\": [\n            {\n                \"specialty\": \"Geneticist\",\n                \"urgency\": \"urgent\",\n                \"reason\": \"Confirm diagnosis and genetic counseling\"\n            },\n            {\n                \"specialty\": \"Neurologist\",\n                \"urgency\": \"urgent\",\n                \"reason\": \"Evaluate muscle function and weakness\"\n            }\n        ]\n    },\n    \"red_flags\": [\n        \"Severe muscle pain and weakness lasting more than a few days\",\n        \"Dark urine with severe muscle symptoms\"\n    ],\n    \"patient_education\": [\n        \"Importance of avoiding intense physical activity\",\n        \"Dietary modifications to manage symptoms\",\n        \"Understanding genetic implications for family planning\"\n    ],\n    \"follow_up\": {\n        \"timing\": \"Within 2 weeks\",\n        \"conditions\": \"Worsening symptoms, new onset of symptoms, or any concerns\"\n    },\n    \"confidence_in_assessment\": 0.8,\n    \"uncertainties\": [\n        \"Precise genetic mutation\",\n        \"Potential co-existing conditions\"\n    ]\n}\n```",
  "latency": 17.782644033432007,
  "timestamp": "2025-08-10T01:12:53.441712",
  "cached_at": "2025-08-10T01:12:53.441719"
}