{
  "content": "{\n    \"primary_diagnosis\": {\n        \"name\": \"Toxic Delirium Due to Methamphetamine Use\",\n        \"confidence\": 0.8,\n        \"icd_code\": \"F11.3\",\n        \"reasoning\": \"Patient's history of methamphetamine use, presentation with paranoid ideation, and physical findings such as scratching marks and hypertension are consistent with toxic delirium due to methamphetamine use\"\n    },\n    \"differential_diagnoses\": [\n        {\n            \"name\": \"Serious Wound Infection\",\n            \"confidence\": 0.6,\n            \"icd_code\": \"I96.1\",\n            \"reasoning\": \"Patient's recent head trauma and presence of scratching marks could be indicative of a serious wound infection\"\n        },\n        {\n            \"name\": \"Migraine with Coma\",\n            \"confidence\": 0.5,\n            \"icd_code\": \"G45.2\",\n            \"reasoning\": \"Patient's visual disturbances and severe headache could be consistent with a migraine with coma, although this is less likely given the presence of other symptoms\"\n        },\n        {\n            \"name\": \"Hypertensive Crisis\",\n            \"confidence\": 0.4,\n            \"icd_code\": \"I13.0\",\n            \"reasoning\": \"Patient's severely elevated blood pressure is a critical finding that requires immediate attention, although it may not be directly related to the presenting symptoms\"\n        }\n    ],\n    \"key_findings\": [\n        \"Extensive scratching marks on the skin\",\n        \"Severely elevated blood pressure (190/110 mmHg)\"\n    ],\n    \"diagnostic_tests\": [\n        {\n            \"test\": \"Complete Blood Count (CBC) and Comprehensive Metabolic Panel (CMP)\",\n            \"purpose\": \"To rule in/out infection, inflammation, and metabolic disturbances\",\n            \"priority\": \"immediate\"\n        },\n        {\n            \"test\": \"Imaging study of the head (CT or MRI) to evaluate for signs of infection or trauma\",\n            \"purpose\": \"To evaluate for signs of infection or trauma\",\n            \"priority\": \"urgent\"\n        }\n    ],\n    \"management_plan\": {\n        \"immediate_actions\": [\n            \"Administer oxygen therapy to manage respiratory status\",\n            \"Initiate blood pressure management with antihypertensives\"\n        ],\n        \"medications\": [\n            {\n                \"drug\": \"Lorazepam\",\n                \"dose\": \"2mg IV\",\n                \"route\": \"IV\",\n                \"duration\": \"As needed\",\n                \"rationale\": \"To manage agitation and delirium\"\n            },\n            {\n                \"drug\": \"Nitroglycerin\",\n                \"dose\": \"10mg sublingual\",\n                \"route\": \"Sublingual\",\n                \"duration\": \"As needed\",\n                \"rationale\": \"To manage hypertension\"\n            },\n            {\n                \"drug\": \"Metronidazole\",\n                \"dose\": \"500mg IV\",\n                \"route\": \"IV\",\n                \"duration\": \"As needed\",\n                \"rationale\": \"To treat potential infection\"\n            }\n        ],\n        \"monitoring\": [\n            \"Vital signs (BP, HR, RR, O2S) every 15 minutes\",\n            \"Oxygen saturation via pulse oximetry\"\n        ],\n        \"consultations\": [\n            {\n                \"specialty\": \"Neurology\",\n                \"urgency\": \"immediate\",\n                \"reason\": \"To evaluate for signs of neurological complications\"\n            }\n        ]\n    },\n    \"red_flags\": [\n        \"Recent head trauma\",\n        \"History of methamphetamine use\"\n    ],\n    \"patient_education\": [\n        \"Patient is at risk for complications from methamphetamine use, including cardiovascular and neurological events\",\n        \"Patient should avoid activities that exacerbate symptoms, and follow-up with a healthcare provider as soon as possible\"\n    ],\n    \"follow_up\": {\n        \"timing\": \"Within 24 hours\",\n        \"conditions\": \"Continued agitation, delirium, or worsening of hypertension\"\n    },\n    \"confidence_in_assessment\": 0.8,\n    \"uncertainties\": [\n        \"Potential for underlying infection or trauma\",\n        \"Limited information about patient's medical history\"\n    ]\n}",
  "error": null,
  "timestamp": "2025-08-09T23:08:48.690267",
  "tokens_used": 2267,
  "latency": 6.984508275985718,
  "model_id": "meta-llama/llama-3.2-3b-instruct:free",
  "cache_version": "v2.0_standardized_json",
  "cached_at": "2025-08-09T23:08:48.690835"
}